celery_tryton.py
celery_tryton-0.4.dist-info/DESCRIPTION.rst
celery_tryton-0.4.dist-info/METADATA
celery_tryton-0.4.dist-info/RECORD
celery_tryton-0.4.dist-info/WHEEL
celery_tryton-0.4.dist-info/metadata.json
celery_tryton-0.4.dist-info/top_level.txt
