Metadata-Version: 2.0
Name: celery-tryton
Version: 0.4
Summary: Celery integration with Tryton
Home-page: http://celery-tryton.b2ck.com/
Author: B2CK
Author-email: info@b2ck.com
License: BSD
Keywords: celery tryton distributed
Platform: any
Classifier: Environment :: Plugins
Classifier: Framework :: Tryton
Classifier: Intended Audience :: Developers
Classifier: License :: OSI Approved :: BSD License
Classifier: Operating System :: OS Independent
Classifier: Programming Language :: Python :: 2.7
Classifier: Programming Language :: Python :: 3.4
Classifier: Programming Language :: Python :: 3.5
Classifier: Programming Language :: Python :: 3.6
Classifier: Topic :: Software Development :: Libraries :: Python Modules
Classifier: Topic :: Software Development :: Object Brokering
Classifier: Topic :: System :: Distributed Computing
Requires-Dist: celery
Requires-Dist: trytond (>=3.0)
